{
  "Área 1: Ciencias Físico-Matemáticas y de las Ingenierías": {
    "UNAM": [
      "Actuaría",
      "Arquitectura",
      "Arquitectura de Paisaje",
      "Ciencia de Datos",
      "Ciencias de la Computación",
      "Ciencias de la Tierra",
      "Diseño Industrial",
      "Física",
      "Física Biomédica",
      "Ingeniería Aeroespacial",
      "Ingeniería Ambiental",
      "Ingeniería Civil",
      "Ingeniería de Minas y Metalurgia",
      "Ingeniería Eléctrica Electrónica",
      "Ingeniería en Computación",
      "Ingeniería en Sistemas Biomédicos",
      "Ingeniería en Telecomunicaciones",
      "Ingeniería Geofísica",
      "Ingeniería Geológica",
      "Ingeniería Geomática",
      "Ingeniería Industrial",
      "Ingeniería Mecánica",
      "Ingeniería Mecatrónica",
      "Ingeniería Petrolera",
      "Ingeniería Química",
      "Ingeniería Química Metalúrgica",
      "Matemáticas",
      "Matemáticas Aplicadas",
      "Urbanismo"
    ],
    "IPN": [
      "Ingeniería en Meteorología",
      "Ingeniería Aeronáutica",
      "Ingeniería Ambiental",
      "Ingeniería Biomédica",
      "Ingeniería Biónica",
      "Ingeniería Bioquímica",
      "Ingeniería Biotecnológica",
      "Ingeniería Civil",
      "Ingeniería Eléctrica",
      "Ingeniería en Alimentos",
      "Ingeniería en Computación",
      "Ingeniería en Comunicaciones y Electrónica",
      "Ingeniería en Control y Automatización",
      "Ingeniería en Energía",
      "Ingeniería en Informática",
      "Ingeniería en Inteligencia Artificial",
      "Ingeniería en Metalurgia y Materiales",
      "Ingeniería en Movilidad Urbana",
      "Ingeniería en Negocios Energéticos Sustentables",
      "Ingeniería en Robótica Industrial",
      "Ingeniería en Sistemas Ambientales",
      "Ingeniería en Sistemas Automotrices",
      "Ingeniería en Sistemas Computacionales",
      "Ingeniería en Sistemas Energéticos y Redes Inteligentes",
      "Ingeniería en Transporte",
      "Ingeniería Farmacéutica",
      "Ingeniería Ferroviaria",
      "Ingeniería Fotónica",
      "Ingeniería Geofísica",
      "Ingeniería Geológica",
      "Ingeniería Industrial",
      "Ingeniería Matemática",
      "Ingeniería Mecánica",
      "Ingeniería Mecatrónica",
      "Ingeniería Metalúrgica",
      "Ingeniería Petrolera",
      "Ingeniería Química Industrial",
      "Ingeniería Química Petrolera",
      "Ingeniería Telemática",
      "Ingeniería Textil",
      "Ingeniería Topográfica y Fotogramétrica",
      "Ingeniero Arquitecto",
      "Licenciatura en Ciencia de Datos",
      "Licenciatura en Ciencias de la Informática",
      "Licenciatura en Física y Matemáticas",
      "Licenciatura en Matemática Algorítmica"
    ],
    "UAM": [
      "Arquitectura",
      "Ciencias Atmosféricas",
      "Computación",
      "Diseño Industrial",
      "Ingeniería Electrónica",
      "Ingeniería Eléctrica",
      "Ingeniería Física",
      "Ingeniería Civil",
      "Ingeniería Industrial",
      "Ingeniería Mecánica",
      "Ingeniería Metalúrgica",
      "Ingeniería Química",
      "Ingeniería en Computación",
      "Ingeniería en Computación y Telecomunicaciones",
      "Ingeniería en Energía",
      "Ingeniería en Sistemas Mecatrónicos",
      "Matemáticas",
      "Matemáticas Aplicadas",
      "Planeación Territorial",
      "Tecnologías y Sistemas de Información",
      "Ingeniería Ambiental",
      "Ingeniería Hidrológica",
      "Ingeniería en Ciencia y Tecnología del Agua"
    ]
  },
  "Área 2: Ciencias Biológicas, Químicas y de la Salud": {
    "UNAM": [
      "Biología",
      "Ciencia de la Nutrición Humana",
      "Ciencia Forense",
      "Cirujano Dentista",
      "Fisioterapia",
      "Investigación Biomédica Básica",
      "Medicina Veterinaria y Zootecnia",
      "Médico Cirujano",
      "Neurociencias",
      "Psicología",
      "Química",
      "Química de Alimentos",
      "Química e Ingeniería en Materiales",
      "Química Farmacéutico Biológica"
    ],
    "IPN": [
      "Licenciatura en Biología",
      "Licenciatura en Enfermería",
      "Licenciatura en Enfermería y Obstetricia",
      "Licenciatura en Nutrición",
      "Licenciatura en Odontología",
      "Licenciatura en Optometría",
      "Licenciatura en Psicología",
      "Médico Cirujano Homeópata",
      "Médico Cirujano Partero",
      "Químico Bacteriólogo y Parasitólogo",
      "Químico Farmacéutico Industrial"
    ],
    "UAM": [
      "Biología",
      "Biología Ambiental",
      "Biología Experimental",
      "Biología Molecular",
      "Ciencia y Tecnología de Alimentos",
      "Enfermería",
      "Estomatología",
      "Agronomía",
      "Hidrobiología",
      "Ingeniería Biológica",
      "Ingeniería Biomédica",
      "Ingeniería Bioquímica Industrial",
      "Ingeniería de los Alimentos",
      "Medicina",
      "Medicina Veterinaria y Zootecnia",
      "Nutrición Humana",
      "Producción Animal",
      "Psicología",
      "Psicología Biomédica",
      "Química",
      "Química Farmacéutica Biológica"
    ]
  },
  "Área 3: Ciencias Sociales": {
    "UNAM": [
      "Administración",
      "Antropología",
      "Ciencias de la Comunicación",
      "Ciencias Políticas y Administración Pública",
      "Contaduría",
      "Derecho",
      "Economía",
      "Geografía",
      "Geografía Aplicada",
      "Informática",
      "Negocios Internacionales",
      "Relaciones Internacionales",
      "Sociología",
      "Trabajo Social"
    ],
    "IPN": [
      "Contador Público",
      "Licenciatura en Administración Industrial",
      "Licenciatura en Administración y Desarrollo Empresarial",
      "Licenciatura en Comercio Internacional",
      "Licenciatura en Contaduría y Finanzas Públicas",
      "Licenciatura en Economía",
      "Licenciatura en Mercadotecnia Digital",
      "Licenciatura en Negocios Digitales",
      "Licenciatura en Negocios Internacionales",
      "Licenciatura en Relaciones Comerciales",
      "Licenciatura en Trabajo Social",
      "Licenciatura en Turismo",
      "Licenciatura en Turismo Sustentable"
    ],
    "UAM": [
      "Administración",
      "Antropología Social",
      "Ciencia Política",
      "Ciencias de la Comunicación",
      "Comunicación Social",
      "Derecho",
      "Economía",
      "Educación y Tecnologías Digitales",
      "Estudios Socioterritoriales",
      "Geografía Humana",
      "Política y Gestión Social",
      "Políticas Públicas",
      "Sociología",
      "Psicología Social"
    ]
  },
  "Área 4: Humanidades y de las Artes": {
    "UNAM": [
      "Administración de Archivos y Gestión Documental",
      "Arte y Diseño",
      "Artes Visuales",
      "Bibliotecología y Estudios de la Información",
      "Cine",
      "Cinematografía",
      "Desarrollo y Gestión Interculturales",
      "Diseño y Comunicación Visual",
      "Estudios Latinoamericanos",
      "Filosofía",
      "Historia",
      "Lengua y Literaturas Hispánicas",
      "Lengua y Literaturas Modernas",
      "Letras Clásicas",
      "Lingüística Aplicada",
      "Literatura Dramática y Teatro",
      "Pedagogía",
      "Teatro y Actuación",
      "Traducción"
    ],
    "IPN": [
      "Licenciatura en Archivonomía",
      "Licenciatura en Biblioteconomía"
    ],
    "UAM": [
      "Arte y Comunicación Digitales",
      "Diseño",
      "Diseño de Proyectos Sustentables",
      "Diseño de la Comunicación Gráfica",
      "Filosofía",
      "Historia",
      "Humanidades",
      "Letras Hispánicas",
      "Lingüística"
    ]
  }
}
